[
  {
    "name": "拉萨市",
    "subCity": [
      "城关区",
      "当雄县",
      "林周县",
      "墨竹工卡县",
      "堆龙德庆区",
      "尼木县",
      "达孜区",
      "曲水县"
    ]
  },
  {
    "name": "林芝市",
    "subCity": [
      "波密县",
      "工布江达县",
      "巴宜区",
      "米林县",
      "墨脱县",
      "朗县",
      "察隅县"
    ]
  },
  {
    "name": "山南市",
    "subCity": [
      "桑日县",
      "加查县",
      "乃东区",
      "扎囊县",
      "贡嘎县",
      "浪卡子县",
      "曲松县",
      "琼结县",
      "措美县",
      "隆子县",
      "洛扎县",
      "错那县"
    ]
  },
  {
    "name": "阿里地区",
    "subCity": [
      "改则县",
      "札达县",
      "措勤县",
      "普兰县",
      "日土县",
      "噶尔县",
      "革吉县"
    ]
  },
  {
    "name": "那曲市",
    "subCity": [
      "安多县",
      "聂荣县",
      "巴青县",
      "申扎县",
      "班戈县",
      "索县",
      "比如县",
      "色尼区",
      "嘉黎县",
      "尼玛县",
      "双湖县"
    ]
  },
  {
    "name": "日喀则市",
    "subCity": [
      "仲巴县",
      "昂仁县",
      "谢通门县",
      "南木林县",
      "萨嘎县",
      "桑珠孜区",
      "拉孜县",
      "仁布县",
      "萨迦县",
      "吉隆县",
      "白朗县",
      "江孜县",
      "聂拉木县",
      "定日县",
      "康马县",
      "岗巴县",
      "定结县",
      "亚东县"
    ]
  },
  {
    "name": "昌都市",
    "subCity": [
      "江达县",
      "丁青县",
      "卡若区",
      "类乌齐县",
      "边坝县",
      "贡觉县",
      "洛隆县",
      "察雅县",
      "八宿县",
      "左贡县",
      "芒康县"
    ]
  }
]
